lab_serializer/__init__.py
lab_serializer/data_packer/__init__.py
lab_serializer/data_packer/consts.py
lab_serializer/data_packer/packer.py
lab_serializer/serializers/__init__.py
lab_serializer/serializers/json_serializer.py
lab_serializer/serializers/serializer_factory.py
lab_serializer/serializers/serializer_meta.py
lab_serializer/serializers/serializer_shell.py
lab_serializer/serializers/xml_serializer.py
serializer_minenkov-1.4.dist-info/METADATA
serializer_minenkov-1.4.dist-info/WHEEL
serializer_minenkov-1.4.dist-info/top_level.txt
serializer_minenkov-1.4.dist-info/RECORD
