Metadata-Version: 2.1
Name: serializer-minenkov
Version: 1.4
Summary: JSON/XML serializer
Author: Yaroslav
